{
  "file_size": 141952249,
  "filename": "T:\\FS\\Reference\\RSImagery\\ProcessedData\\r06\\R06_DRM_Deliverables\\PointCloud\\WAW_2007_RiverCorridor_Wenatchee/47120-d3-nw-BC.las",
  "metadata":
  {
    "comp_spatialreference": "",
    "compressed": false,
    "copc": false,
    "count": 5069715,
    "creation_doy": 0,
    "creation_year": 0,
    "dataformat_id": 1,
    "dataoffset": 229,
    "filesource_id": 0,
    "header_size": 227,
    "major_version": 1,
    "maxx": 698897.65,
    "maxy": 5261854.91,
    "maxz": 289.47,
    "minor_version": 0,
    "minx": 697677.29,
    "miny": 5260577.28,
    "minz": 195.14,
    "offset_x": 0,
    "offset_y": 0,
    "offset_z": 0,
    "point_length": 28,
    "project_id": "00000000-0000-0000-0000-000000000000",
    "scale_x": 0.01,
    "scale_y": 0.01,
    "scale_z": 0.01,
    "software_id": "TerraScan",
    "spatialreference": "",
    "srs":
    {
      "compoundwkt": "",
      "horizontal": "",
      "isgeocentric": false,
      "isgeographic": false,
      "json":
      {
      },
      "prettycompoundwkt": "",
      "prettywkt": "",
      "proj4": "",
      "units":
      {
        "horizontal": "unknown",
        "vertical": ""
      },
      "vertical": "",
      "wkt": ""
    },
    "system_id": ""
  },
  "now": "2025-04-08T09:19:34-0400",
  "pdal_version": "2.8.4 (git-version: Release)",
  "reader": "readers.las"
}
